odoo/addons/purchase_receipt_expectation_manual_split/README.rst
odoo/addons/purchase_receipt_expectation_manual_split/__init__.py
odoo/addons/purchase_receipt_expectation_manual_split/__manifest__.py
odoo/addons/purchase_receipt_expectation_manual_split/i18n/fr.po
odoo/addons/purchase_receipt_expectation_manual_split/i18n/purchase_receipt_expectation_manual_split.pot
odoo/addons/purchase_receipt_expectation_manual_split/models/__init__.py
odoo/addons/purchase_receipt_expectation_manual_split/models/purchase_order_line.py
odoo/addons/purchase_receipt_expectation_manual_split/models/stock_move.py
odoo/addons/purchase_receipt_expectation_manual_split/readme/CONTRIBUTORS.rst
odoo/addons/purchase_receipt_expectation_manual_split/readme/DESCRIPTION.rst
odoo/addons/purchase_receipt_expectation_manual_split/readme/USAGE.rst
odoo/addons/purchase_receipt_expectation_manual_split/static/description/icon.png
odoo/addons/purchase_receipt_expectation_manual_split/static/description/index.html
odoo/addons/purchase_receipt_expectation_manual_split/tests/__init__.py
odoo/addons/purchase_receipt_expectation_manual_split/tests/test_purchase_receipt_expectation_manual_split.py
odoo/addons/purchase_receipt_expectation_manual_split/wizards/__init__.py
odoo/addons/purchase_receipt_expectation_manual_split/wizards/purchase_order_manual_receipt_line.py
odoo_addon_purchase_receipt_expectation_manual_split-15.0.2.0.0.2.dist-info/METADATA
odoo_addon_purchase_receipt_expectation_manual_split-15.0.2.0.0.2.dist-info/WHEEL
odoo_addon_purchase_receipt_expectation_manual_split-15.0.2.0.0.2.dist-info/top_level.txt
odoo_addon_purchase_receipt_expectation_manual_split-15.0.2.0.0.2.dist-info/RECORD
