Metadata-Version: 2.1
Name: odoo-addon-purchase-receipt-expectation-manual-split
Version: 15.0.2.0.0.2
Summary: Purchase Receipt Expectation - Manual w/ Split
Home-page: https://github.com/OCA/purchase-workflow
Author: Camptocamp SA, Odoo Community Association (OCA)
Author-email: support@odoo-community.org
License: AGPL-3
Platform: UNKNOWN
Classifier: Programming Language :: Python
Classifier: Framework :: Odoo
Classifier: Framework :: Odoo :: 15.0
Classifier: License :: OSI Approved :: GNU Affero General Public License v3
Requires-Python: >=3.8
Requires-Dist: odoo-addon-purchase-receipt-expectation-manual <15.1dev,>=15.0dev
Requires-Dist: odoo <15.1dev,>=15.0a
